{"cameraMode":{"drawMode":0,"name":"Shaded","section":"Shading Mode"},"sceneLighting":true,"audioPlay":false,"sceneViewState":{"m_AlwaysRefresh":false,"showFog":true,"showSkybox":true,"showFlares":true,"showImageEffects":true,"showParticleSystems":true,"showVisualEffectGraphs":true,"m_FxEnabled":false},"in2DMode":false,"pivot":{"x":939.0394287109375,"y":494.399169921875,"z":-516.2904052734375},"rotation":{"x":-0.0013415616704151035,"y":0.9948099851608276,"z":-0.09880425781011582,"w":-0.01223172340542078},"size":889.3925170898438,"orthographic":false}